setup.py
SimpleThreading/__init__.py
ThreadDownloader2508.egg-info/PKG-INFO
ThreadDownloader2508.egg-info/SOURCES.txt
ThreadDownloader2508.egg-info/dependency_links.txt
ThreadDownloader2508.egg-info/top_level.txt