Metadata-Version: 1.0
Name: ThreadDownloader2508
Version: 1.0.0
Summary: My first py dist
Home-page: UNKNOWN
Author: UNKNOWN
Author-email: UNKNOWN
License: UNKNOWN
Platform: UNKNOWN
